{
	"$schema": "http://schema.management.azure.com/schemas/2015-01-01/deploymentTemplate.json#",
	"contentVersion": "1.0.0.0",
	"parameters": {
		"factoryName": {
			"type": "string",
			"metadata": "Data Factory name",
			"defaultValue": "adf-mycpayrollsharan"
		},
		"ls_adls_accountKey": {
			"type": "secureString",
			"metadata": "Secure string for 'accountKey' of 'ls_adls'"
		},
		"ls_sqlsb_password": {
			"type": "secureString",
			"metadata": "Secure string for 'password' of 'ls_sqlsb'"
		},
		"ls_synapse_password": {
			"type": "secureString",
			"metadata": "Secure string for 'password' of 'ls_synapse'"
		},
		"ls_adls_properties_typeProperties_url": {
			"type": "string",
			"defaultValue": "https://adlsnycpayrollsharanv.dfs.core.windows.net/"
		},
		"ls_sqlsb_properties_typeProperties_server": {
			"type": "string",
			"defaultValue": "sqlserver-sharan.database.windows.net"
		},
		"ls_sqlsb_properties_typeProperties_database": {
			"type": "string",
			"defaultValue": "db_nycpayroll"
		},
		"ls_sqlsb_properties_typeProperties_userName": {
			"type": "string",
			"defaultValue": "azureadmin"
		},
		"ls_synapse_properties_typeProperties_server": {
			"type": "string",
			"defaultValue": "synapse-nycpayrollsharan.sql.azuresynapse.net"
		},
		"ls_synapse_properties_typeProperties_database": {
			"type": "string",
			"defaultValue": "sqlpool1"
		},
		"ls_synapse_properties_typeProperties_userName": {
			"type": "string",
			"defaultValue": "azureadmin"
		}
	},
	"variables": {
		"factoryId": "[concat('Microsoft.DataFactory/factories/', parameters('factoryName'))]"
	},
	"resources": [
		{
			"name": "[concat(parameters('factoryName'), '/ls_adls')]",
			"type": "Microsoft.DataFactory/factories/linkedServices",
			"apiVersion": "2018-06-01",
			"properties": {
				"annotations": [],
				"type": "AzureBlobFS",
				"typeProperties": {
					"url": "[parameters('ls_adls_properties_typeProperties_url')]",
					"accountKey": {
						"type": "SecureString",
						"value": "[parameters('ls_adls_accountKey')]"
					}
				}
			},
			"dependsOn": []
		},
		{
			"name": "[concat(parameters('factoryName'), '/ls_sqlsb')]",
			"type": "Microsoft.DataFactory/factories/linkedServices",
			"apiVersion": "2018-06-01",
			"properties": {
				"annotations": [],
				"type": "AzureSqlDatabase",
				"typeProperties": {
					"server": "[parameters('ls_sqlsb_properties_typeProperties_server')]",
					"database": "[parameters('ls_sqlsb_properties_typeProperties_database')]",
					"encrypt": "mandatory",
					"trustServerCertificate": false,
					"authenticationType": "SQL",
					"userName": "[parameters('ls_sqlsb_properties_typeProperties_userName')]",
					"password": {
						"type": "SecureString",
						"value": "[parameters('ls_sqlsb_password')]"
					}
				}
			},
			"dependsOn": []
		},
		{
			"name": "[concat(parameters('factoryName'), '/ls_synapse')]",
			"type": "Microsoft.DataFactory/factories/linkedServices",
			"apiVersion": "2018-06-01",
			"properties": {
				"annotations": [],
				"type": "AzureSqlDW",
				"typeProperties": {
					"server": "[parameters('ls_synapse_properties_typeProperties_server')]",
					"database": "[parameters('ls_synapse_properties_typeProperties_database')]",
					"encrypt": "mandatory",
					"trustServerCertificate": false,
					"authenticationType": "SQL",
					"userName": "[parameters('ls_synapse_properties_typeProperties_userName')]",
					"password": {
						"type": "SecureString",
						"value": "[parameters('ls_synapse_password')]"
					}
				}
			},
			"dependsOn": []
		},
		{
			"name": "[concat(parameters('factoryName'), '/ds_AgencyMaster')]",
			"type": "Microsoft.DataFactory/factories/datasets",
			"apiVersion": "2018-06-01",
			"properties": {
				"linkedServiceName": {
					"referenceName": "ls_adls",
					"type": "LinkedServiceReference"
				},
				"annotations": [],
				"type": "DelimitedText",
				"typeProperties": {
					"location": {
						"type": "AzureBlobFSLocation",
						"fileName": "AgencyMaster.csv",
						"folderPath": "dirpayrollfiles",
						"fileSystem": "nycpayrollcontainer"
					},
					"columnDelimiter": ",",
					"escapeChar": "\\",
					"firstRowAsHeader": true,
					"quoteChar": "\""
				},
				"schema": [
					{
						"name": "AgencyID",
						"type": "String"
					},
					{
						"name": "AgencyName",
						"type": "String"
					}
				]
			},
			"dependsOn": [
				"[concat(variables('factoryId'), '/linkedServices/ls_adls')]"
			]
		},
		{
			"name": "[concat(parameters('factoryName'), '/ds_EmpMaster')]",
			"type": "Microsoft.DataFactory/factories/datasets",
			"apiVersion": "2018-06-01",
			"properties": {
				"linkedServiceName": {
					"referenceName": "ls_adls",
					"type": "LinkedServiceReference"
				},
				"annotations": [],
				"type": "DelimitedText",
				"typeProperties": {
					"location": {
						"type": "AzureBlobFSLocation",
						"fileName": "EmpMaster.csv",
						"folderPath": "dirpayrollfiles",
						"fileSystem": "nycpayrollcontainer"
					},
					"columnDelimiter": ",",
					"escapeChar": "\\",
					"firstRowAsHeader": true,
					"quoteChar": "\""
				},
				"schema": [
					{
						"name": "EmployeeID",
						"type": "String"
					},
					{
						"name": "LastName",
						"type": "String"
					},
					{
						"name": "FirstName",
						"type": "String"
					}
				]
			},
			"dependsOn": [
				"[concat(variables('factoryId'), '/linkedServices/ls_adls')]"
			]
		},
		{
			"name": "[concat(parameters('factoryName'), '/ds_Historical_Payroll')]",
			"type": "Microsoft.DataFactory/factories/datasets",
			"apiVersion": "2018-06-01",
			"properties": {
				"linkedServiceName": {
					"referenceName": "ls_adls",
					"type": "LinkedServiceReference"
				},
				"annotations": [],
				"type": "DelimitedText",
				"typeProperties": {
					"location": {
						"type": "AzureBlobFSLocation",
						"fileName": "nycpayroll_2020.csv",
						"folderPath": "dirhistoryfiles",
						"fileSystem": "nycpayrollcontainer"
					},
					"columnDelimiter": ",",
					"escapeChar": "\\",
					"firstRowAsHeader": true,
					"quoteChar": "\""
				},
				"schema": [
					{
						"name": "FiscalYear",
						"type": "String"
					},
					{
						"name": "PayrollNumber",
						"type": "String"
					},
					{
						"name": "AgencyID",
						"type": "String"
					},
					{
						"name": "AgencyName",
						"type": "String"
					},
					{
						"name": "EmployeeID",
						"type": "String"
					},
					{
						"name": "LastName",
						"type": "String"
					},
					{
						"name": "FirstName",
						"type": "String"
					},
					{
						"name": "AgencyStartDate",
						"type": "String"
					},
					{
						"name": "WorkLocationBorough",
						"type": "String"
					},
					{
						"name": "TitleCode",
						"type": "String"
					},
					{
						"name": "TitleDescription",
						"type": "String"
					},
					{
						"name": "LeaveStatusasofJune30",
						"type": "String"
					},
					{
						"name": "BaseSalary",
						"type": "String"
					},
					{
						"name": "PayBasis",
						"type": "String"
					},
					{
						"name": "RegularHours",
						"type": "String"
					},
					{
						"name": "RegularGrossPaid",
						"type": "String"
					},
					{
						"name": "OTHours",
						"type": "String"
					},
					{
						"name": "TotalOTPaid",
						"type": "String"
					},
					{
						"name": "TotalOtherPay",
						"type": "String"
					}
				]
			},
			"dependsOn": [
				"[concat(variables('factoryId'), '/linkedServices/ls_adls')]"
			]
		},
		{
			"name": "[concat(parameters('factoryName'), '/ds_SYN_Payroll_Summary')]",
			"type": "Microsoft.DataFactory/factories/datasets",
			"apiVersion": "2018-06-01",
			"properties": {
				"linkedServiceName": {
					"referenceName": "ls_synapse",
					"type": "LinkedServiceReference"
				},
				"annotations": [],
				"type": "AzureSqlDWTable",
				"schema": [
					{
						"name": "FiscalYear",
						"type": "int",
						"precision": 10
					},
					{
						"name": "AgencyName",
						"type": "varchar"
					},
					{
						"name": "TotalPaid",
						"type": "float",
						"precision": 15
					}
				],
				"typeProperties": {
					"schema": "dbo",
					"table": "NYC_Payroll_Summary"
				}
			},
			"dependsOn": [
				"[concat(variables('factoryId'), '/linkedServices/ls_synapse')]"
			]
		},
		{
			"name": "[concat(parameters('factoryName'), '/ds_TitleMaster')]",
			"type": "Microsoft.DataFactory/factories/datasets",
			"apiVersion": "2018-06-01",
			"properties": {
				"linkedServiceName": {
					"referenceName": "ls_adls",
					"type": "LinkedServiceReference"
				},
				"annotations": [],
				"type": "DelimitedText",
				"typeProperties": {
					"location": {
						"type": "AzureBlobFSLocation",
						"fileName": "TitleMaster.csv",
						"folderPath": "dirpayrollfiles",
						"fileSystem": "nycpayrollcontainer"
					},
					"columnDelimiter": ",",
					"escapeChar": "\\",
					"firstRowAsHeader": true,
					"quoteChar": "\""
				},
				"schema": [
					{
						"name": "TitleCode",
						"type": "String"
					},
					{
						"name": "TitleDescription",
						"type": "String"
					}
				]
			},
			"dependsOn": [
				"[concat(variables('factoryId'), '/linkedServices/ls_adls')]"
			]
		},
		{
			"name": "[concat(parameters('factoryName'), '/ds_nycpayroll_2021')]",
			"type": "Microsoft.DataFactory/factories/datasets",
			"apiVersion": "2018-06-01",
			"properties": {
				"linkedServiceName": {
					"referenceName": "ls_adls",
					"type": "LinkedServiceReference"
				},
				"annotations": [],
				"type": "DelimitedText",
				"typeProperties": {
					"location": {
						"type": "AzureBlobFSLocation",
						"fileName": "nycpayroll_2021.csv",
						"folderPath": "dirpayrollfiles",
						"fileSystem": "nycpayrollcontainer"
					},
					"columnDelimiter": ",",
					"escapeChar": "\\",
					"firstRowAsHeader": true,
					"quoteChar": "\""
				},
				"schema": [
					{
						"name": "FiscalYear",
						"type": "String"
					},
					{
						"name": "PayrollNumber",
						"type": "String"
					},
					{
						"name": "AgencyCode",
						"type": "String"
					},
					{
						"name": "AgencyName",
						"type": "String"
					},
					{
						"name": "EmployeeID",
						"type": "String"
					},
					{
						"name": "LastName",
						"type": "String"
					},
					{
						"name": "FirstName",
						"type": "String"
					},
					{
						"name": "AgencyStartDate",
						"type": "String"
					},
					{
						"name": "WorkLocationBorough",
						"type": "String"
					},
					{
						"name": "TitleCode",
						"type": "String"
					},
					{
						"name": "TitleDescription",
						"type": "String"
					},
					{
						"name": "LeaveStatusasofJune30",
						"type": "String"
					},
					{
						"name": "BaseSalary",
						"type": "String"
					},
					{
						"name": "PayBasis",
						"type": "String"
					},
					{
						"name": "RegularHours",
						"type": "String"
					},
					{
						"name": "RegularGrossPaid",
						"type": "String"
					},
					{
						"name": "OTHours",
						"type": "String"
					},
					{
						"name": "TotalOTPaid",
						"type": "String"
					},
					{
						"name": "TotalOtherPay",
						"type": "String"
					}
				]
			},
			"dependsOn": [
				"[concat(variables('factoryId'), '/linkedServices/ls_adls')]"
			]
		},
		{
			"name": "[concat(parameters('factoryName'), '/ds_sql_nyc_payroll')]",
			"type": "Microsoft.DataFactory/factories/datasets",
			"apiVersion": "2018-06-01",
			"properties": {
				"linkedServiceName": {
					"referenceName": "ls_sqlsb",
					"type": "LinkedServiceReference"
				},
				"annotations": [],
				"type": "AzureSqlTable",
				"schema": [
					{
						"name": "FiscalYear",
						"type": "int",
						"precision": 10
					},
					{
						"name": "PayrollNumber",
						"type": "int",
						"precision": 10
					},
					{
						"name": "AgencyID",
						"type": "varchar"
					},
					{
						"name": "AgencyName",
						"type": "varchar"
					},
					{
						"name": "EmployeeID",
						"type": "varchar"
					},
					{
						"name": "LastName",
						"type": "varchar"
					},
					{
						"name": "FirstName",
						"type": "varchar"
					},
					{
						"name": "AgencyStartDate",
						"type": "date"
					},
					{
						"name": "WorkLocationBorough",
						"type": "varchar"
					},
					{
						"name": "TitleCode",
						"type": "varchar"
					},
					{
						"name": "TitleDescription",
						"type": "varchar"
					},
					{
						"name": "LeaveStatusasofJune30",
						"type": "varchar"
					},
					{
						"name": "BaseSalary",
						"type": "float",
						"precision": 15
					},
					{
						"name": "PayBasis",
						"type": "varchar"
					},
					{
						"name": "RegularHours",
						"type": "float",
						"precision": 15
					},
					{
						"name": "RegularGrossPaid",
						"type": "float",
						"precision": 15
					},
					{
						"name": "OTHours",
						"type": "float",
						"precision": 15
					},
					{
						"name": "TotalOTPaid",
						"type": "float",
						"precision": 15
					},
					{
						"name": "TotalOtherPay",
						"type": "float",
						"precision": 15
					}
				],
				"typeProperties": {
					"schema": "dbo",
					"table": "NYC_Payroll_Data"
				}
			},
			"dependsOn": [
				"[concat(variables('factoryId'), '/linkedServices/ls_sqlsb')]"
			]
		},
		{
			"name": "[concat(parameters('factoryName'), '/ds_synapse_AGENCY_MD')]",
			"type": "Microsoft.DataFactory/factories/datasets",
			"apiVersion": "2018-06-01",
			"properties": {
				"linkedServiceName": {
					"referenceName": "ls_synapse",
					"type": "LinkedServiceReference"
				},
				"annotations": [],
				"type": "AzureSqlDWTable",
				"schema": [
					{
						"name": "AgencyID",
						"type": "varchar"
					},
					{
						"name": "AgencyName",
						"type": "varchar"
					}
				],
				"typeProperties": {
					"schema": "dbo",
					"table": "NYC_Payroll_AGENCY_MD"
				}
			},
			"dependsOn": [
				"[concat(variables('factoryId'), '/linkedServices/ls_synapse')]"
			]
		},
		{
			"name": "[concat(parameters('factoryName'), '/ds_synapse_EMP_MD')]",
			"type": "Microsoft.DataFactory/factories/datasets",
			"apiVersion": "2018-06-01",
			"properties": {
				"linkedServiceName": {
					"referenceName": "ls_synapse",
					"type": "LinkedServiceReference"
				},
				"annotations": [],
				"type": "AzureSqlDWTable",
				"schema": [
					{
						"name": "EmployeeID",
						"type": "varchar"
					},
					{
						"name": "LastName",
						"type": "varchar"
					},
					{
						"name": "FirstName",
						"type": "varchar"
					}
				],
				"typeProperties": {
					"schema": "dbo",
					"table": "NYC_Payroll_EMP_MD"
				}
			},
			"dependsOn": [
				"[concat(variables('factoryId'), '/linkedServices/ls_synapse')]"
			]
		},
		{
			"name": "[concat(parameters('factoryName'), '/ds_synapse_SYN_Payroll')]",
			"type": "Microsoft.DataFactory/factories/datasets",
			"apiVersion": "2018-06-01",
			"properties": {
				"linkedServiceName": {
					"referenceName": "ls_synapse",
					"type": "LinkedServiceReference"
				},
				"annotations": [],
				"type": "AzureSqlDWTable",
				"schema": [
					{
						"name": "FiscalYear",
						"type": "int",
						"precision": 10
					},
					{
						"name": "PayrollNumber",
						"type": "int",
						"precision": 10
					},
					{
						"name": "AgencyID",
						"type": "varchar"
					},
					{
						"name": "AgencyName",
						"type": "varchar"
					},
					{
						"name": "EmployeeID",
						"type": "varchar"
					},
					{
						"name": "LastName",
						"type": "varchar"
					},
					{
						"name": "FirstName",
						"type": "varchar"
					},
					{
						"name": "AgencyStartDate",
						"type": "date"
					},
					{
						"name": "WorkLocationBorough",
						"type": "varchar"
					},
					{
						"name": "TitleCode",
						"type": "varchar"
					},
					{
						"name": "TitleDescription",
						"type": "varchar"
					},
					{
						"name": "LeaveStatusasofJune30",
						"type": "varchar"
					},
					{
						"name": "BaseSalary",
						"type": "float",
						"precision": 15
					},
					{
						"name": "PayBasis",
						"type": "varchar"
					},
					{
						"name": "RegularHours",
						"type": "float",
						"precision": 15
					},
					{
						"name": "RegularGrossPaid",
						"type": "float",
						"precision": 15
					},
					{
						"name": "OTHours",
						"type": "float",
						"precision": 15
					},
					{
						"name": "TotalOTPaid",
						"type": "float",
						"precision": 15
					},
					{
						"name": "TotalOtherPay",
						"type": "float",
						"precision": 15
					}
				],
				"typeProperties": {
					"schema": "dbo",
					"table": "NYC_Payroll_Data"
				}
			},
			"dependsOn": [
				"[concat(variables('factoryId'), '/linkedServices/ls_synapse')]"
			]
		},
		{
			"name": "[concat(parameters('factoryName'), '/ds_synapse_TITLE_MD')]",
			"type": "Microsoft.DataFactory/factories/datasets",
			"apiVersion": "2018-06-01",
			"properties": {
				"linkedServiceName": {
					"referenceName": "ls_synapse",
					"type": "LinkedServiceReference"
				},
				"annotations": [],
				"type": "AzureSqlDWTable",
				"schema": [
					{
						"name": "TitleCode",
						"type": "varchar"
					},
					{
						"name": "TitleDescription",
						"type": "varchar"
					}
				],
				"typeProperties": {
					"schema": "dbo",
					"table": "NYC_Payroll_TITLE_MD"
				}
			},
			"dependsOn": [
				"[concat(variables('factoryId'), '/linkedServices/ls_synapse')]"
			]
		},
		{
			"name": "[concat(parameters('factoryName'), '/dataflow_load_2021_nycpayroll_sqldb_to_synapse')]",
			"type": "Microsoft.DataFactory/factories/dataflows",
			"apiVersion": "2018-06-01",
			"properties": {
				"type": "MappingDataFlow",
				"typeProperties": {
					"sources": [
						{
							"dataset": {
								"referenceName": "ds_sql_nyc_payroll",
								"type": "DatasetReference"
							},
							"name": "source1"
						}
					],
					"sinks": [
						{
							"dataset": {
								"referenceName": "ds_synapse_SYN_Payroll",
								"type": "DatasetReference"
							},
							"name": "sink1"
						}
					],
					"transformations": [],
					"scriptLines": [
						"source(output(",
						"          FiscalYear as integer,",
						"          PayrollNumber as integer,",
						"          AgencyID as string,",
						"          AgencyName as string,",
						"          EmployeeID as string,",
						"          LastName as string,",
						"          FirstName as string,",
						"          AgencyStartDate as date,",
						"          WorkLocationBorough as string,",
						"          TitleCode as string,",
						"          TitleDescription as string,",
						"          LeaveStatusasofJune30 as string,",
						"          BaseSalary as double,",
						"          PayBasis as string,",
						"          RegularHours as double,",
						"          RegularGrossPaid as double,",
						"          OTHours as double,",
						"          TotalOTPaid as double,",
						"          TotalOtherPay as double",
						"     ),",
						"     allowSchemaDrift: true,",
						"     validateSchema: false,",
						"     isolationLevel: 'READ_UNCOMMITTED',",
						"     format: 'table') ~> source1",
						"source1 sink(allowSchemaDrift: true,",
						"     validateSchema: false,",
						"     input(",
						"          FiscalYear as integer,",
						"          PayrollNumber as integer,",
						"          AgencyID as string,",
						"          AgencyName as string,",
						"          EmployeeID as string,",
						"          LastName as string,",
						"          FirstName as string,",
						"          AgencyStartDate as date,",
						"          WorkLocationBorough as string,",
						"          TitleCode as string,",
						"          TitleDescription as string,",
						"          LeaveStatusasofJune30 as string,",
						"          BaseSalary as double,",
						"          PayBasis as string,",
						"          RegularHours as double,",
						"          RegularGrossPaid as double,",
						"          OTHours as double,",
						"          TotalOTPaid as double,",
						"          TotalOtherPay as double",
						"     ),",
						"     deletable:false,",
						"     insertable:true,",
						"     updateable:false,",
						"     upsertable:false,",
						"     format: 'table',",
						"     staged: true,",
						"     allowCopyCommand: true,",
						"     skipDuplicateMapInputs: true,",
						"     skipDuplicateMapOutputs: true,",
						"     errorHandlingOption: 'stopOnFirstError',",
						"     mapColumn(",
						"          FiscalYear,",
						"          PayrollNumber,",
						"          AgencyID,",
						"          AgencyName,",
						"          EmployeeID,",
						"          LastName,",
						"          FirstName,",
						"          AgencyStartDate,",
						"          WorkLocationBorough,",
						"          TitleCode,",
						"          TitleDescription,",
						"          LeaveStatusasofJune30,",
						"          BaseSalary,",
						"          PayBasis,",
						"          RegularHours,",
						"          RegularGrossPaid,",
						"          OTHours,",
						"          TotalOTPaid,",
						"          TotalOtherPay",
						"     )) ~> sink1"
					]
				}
			},
			"dependsOn": [
				"[concat(variables('factoryId'), '/datasets/ds_sql_nyc_payroll')]",
				"[concat(variables('factoryId'), '/datasets/ds_synapse_SYN_Payroll')]"
			]
		},
		{
			"name": "[concat(parameters('factoryName'), '/dataflow_load_2021_nycpayroll_to_sqldb')]",
			"type": "Microsoft.DataFactory/factories/dataflows",
			"apiVersion": "2018-06-01",
			"properties": {
				"type": "MappingDataFlow",
				"typeProperties": {
					"sources": [
						{
							"dataset": {
								"referenceName": "ds_nycpayroll_2021",
								"type": "DatasetReference"
							},
							"name": "sourcenycpayroll2021"
						}
					],
					"sinks": [
						{
							"dataset": {
								"referenceName": "ds_sql_nyc_payroll",
								"type": "DatasetReference"
							},
							"name": "sinknycpayroll"
						}
					],
					"transformations": [],
					"scriptLines": [
						"source(output(",
						"          FiscalYear as string,",
						"          PayrollNumber as string,",
						"          AgencyCode as string,",
						"          AgencyName as string,",
						"          EmployeeID as string,",
						"          LastName as string,",
						"          FirstName as string,",
						"          AgencyStartDate as string,",
						"          WorkLocationBorough as string,",
						"          TitleCode as string,",
						"          TitleDescription as string,",
						"          LeaveStatusasofJune30 as string,",
						"          BaseSalary as string,",
						"          PayBasis as string,",
						"          RegularHours as string,",
						"          RegularGrossPaid as string,",
						"          OTHours as string,",
						"          TotalOTPaid as string,",
						"          TotalOtherPay as string",
						"     ),",
						"     allowSchemaDrift: true,",
						"     validateSchema: false,",
						"     ignoreNoFilesFound: false) ~> sourcenycpayroll2021",
						"sourcenycpayroll2021 sink(allowSchemaDrift: true,",
						"     validateSchema: false,",
						"     input(",
						"          FiscalYear as integer,",
						"          PayrollNumber as integer,",
						"          AgencyID as string,",
						"          AgencyName as string,",
						"          EmployeeID as string,",
						"          LastName as string,",
						"          FirstName as string,",
						"          AgencyStartDate as date,",
						"          WorkLocationBorough as string,",
						"          TitleCode as string,",
						"          TitleDescription as string,",
						"          LeaveStatusasofJune30 as string,",
						"          BaseSalary as double,",
						"          PayBasis as string,",
						"          RegularHours as double,",
						"          RegularGrossPaid as double,",
						"          OTHours as double,",
						"          TotalOTPaid as double,",
						"          TotalOtherPay as double",
						"     ),",
						"     deletable:false,",
						"     insertable:true,",
						"     updateable:false,",
						"     upsertable:false,",
						"     format: 'table',",
						"     skipDuplicateMapInputs: true,",
						"     skipDuplicateMapOutputs: true,",
						"     errorHandlingOption: 'stopOnFirstError',",
						"     mapColumn(",
						"          FiscalYear,",
						"          PayrollNumber,",
						"          AgencyID = AgencyCode,",
						"          AgencyName,",
						"          EmployeeID,",
						"          LastName,",
						"          FirstName,",
						"          AgencyStartDate,",
						"          WorkLocationBorough,",
						"          TitleCode,",
						"          TitleDescription,",
						"          LeaveStatusasofJune30,",
						"          BaseSalary,",
						"          PayBasis,",
						"          RegularHours,",
						"          RegularGrossPaid,",
						"          OTHours,",
						"          TotalOTPaid,",
						"          TotalOtherPay",
						"     )) ~> sinknycpayroll"
					]
				}
			},
			"dependsOn": [
				"[concat(variables('factoryId'), '/datasets/ds_nycpayroll_2021')]",
				"[concat(variables('factoryId'), '/datasets/ds_sql_nyc_payroll')]"
			]
		},
		{
			"name": "[concat(parameters('factoryName'), '/dataflow_load_agency_MD_to_synapse')]",
			"type": "Microsoft.DataFactory/factories/dataflows",
			"apiVersion": "2018-06-01",
			"properties": {
				"type": "MappingDataFlow",
				"typeProperties": {
					"sources": [
						{
							"dataset": {
								"referenceName": "ds_AgencyMaster",
								"type": "DatasetReference"
							},
							"name": "source1"
						}
					],
					"sinks": [
						{
							"dataset": {
								"referenceName": "ds_synapse_AGENCY_MD",
								"type": "DatasetReference"
							},
							"name": "sink1"
						}
					],
					"transformations": [],
					"scriptLines": [
						"source(output(",
						"          AgencyID as integer,",
						"          AgencyName as string",
						"     ),",
						"     allowSchemaDrift: true,",
						"     validateSchema: false,",
						"     ignoreNoFilesFound: false) ~> source1",
						"source1 sink(allowSchemaDrift: true,",
						"     validateSchema: false,",
						"     input(",
						"          AgencyID as string,",
						"          AgencyName as string",
						"     ),",
						"     deletable:false,",
						"     insertable:true,",
						"     updateable:false,",
						"     upsertable:false,",
						"     format: 'table',",
						"     staged: true,",
						"     allowCopyCommand: true,",
						"     skipDuplicateMapInputs: true,",
						"     skipDuplicateMapOutputs: true,",
						"     errorHandlingOption: 'stopOnFirstError',",
						"     mapColumn(",
						"          AgencyID,",
						"          AgencyName",
						"     )) ~> sink1"
					]
				}
			},
			"dependsOn": [
				"[concat(variables('factoryId'), '/datasets/ds_AgencyMaster')]",
				"[concat(variables('factoryId'), '/datasets/ds_synapse_AGENCY_MD')]"
			]
		},
		{
			"name": "[concat(parameters('factoryName'), '/dataflow_load_emp_md_to_synapse')]",
			"type": "Microsoft.DataFactory/factories/dataflows",
			"apiVersion": "2018-06-01",
			"properties": {
				"type": "MappingDataFlow",
				"typeProperties": {
					"sources": [
						{
							"dataset": {
								"referenceName": "ds_EmpMaster",
								"type": "DatasetReference"
							},
							"name": "source1"
						}
					],
					"sinks": [
						{
							"dataset": {
								"referenceName": "ds_synapse_EMP_MD",
								"type": "DatasetReference"
							},
							"name": "sink1"
						}
					],
					"transformations": [],
					"scriptLines": [
						"source(output(",
						"          EmployeeID as integer,",
						"          LastName as string,",
						"          FirstName as string",
						"     ),",
						"     allowSchemaDrift: true,",
						"     validateSchema: false,",
						"     ignoreNoFilesFound: false) ~> source1",
						"source1 sink(allowSchemaDrift: true,",
						"     validateSchema: false,",
						"     input(",
						"          EmployeeID as string,",
						"          LastName as string,",
						"          FirstName as string",
						"     ),",
						"     deletable:false,",
						"     insertable:true,",
						"     updateable:false,",
						"     upsertable:false,",
						"     format: 'table',",
						"     staged: true,",
						"     allowCopyCommand: true,",
						"     skipDuplicateMapInputs: true,",
						"     skipDuplicateMapOutputs: true,",
						"     errorHandlingOption: 'stopOnFirstError',",
						"     mapColumn(",
						"          EmployeeID,",
						"          LastName,",
						"          FirstName",
						"     )) ~> sink1"
					]
				}
			},
			"dependsOn": [
				"[concat(variables('factoryId'), '/datasets/ds_EmpMaster')]",
				"[concat(variables('factoryId'), '/datasets/ds_synapse_EMP_MD')]"
			]
		},
		{
			"name": "[concat(parameters('factoryName'), '/dataflow_load_title_MD_to_synapse')]",
			"type": "Microsoft.DataFactory/factories/dataflows",
			"apiVersion": "2018-06-01",
			"properties": {
				"type": "MappingDataFlow",
				"typeProperties": {
					"sources": [
						{
							"dataset": {
								"referenceName": "ds_TitleMaster",
								"type": "DatasetReference"
							},
							"name": "source1"
						}
					],
					"sinks": [
						{
							"dataset": {
								"referenceName": "ds_synapse_TITLE_MD",
								"type": "DatasetReference"
							},
							"name": "sink1"
						}
					],
					"transformations": [],
					"scriptLines": [
						"source(output(",
						"          TitleCode as integer,",
						"          TitleDescription as string",
						"     ),",
						"     allowSchemaDrift: true,",
						"     validateSchema: false,",
						"     ignoreNoFilesFound: false) ~> source1",
						"source1 sink(allowSchemaDrift: true,",
						"     validateSchema: false,",
						"     input(",
						"          TitleCode as string,",
						"          TitleDescription as string",
						"     ),",
						"     deletable:false,",
						"     insertable:true,",
						"     updateable:false,",
						"     upsertable:false,",
						"     format: 'table',",
						"     staged: true,",
						"     allowCopyCommand: true,",
						"     skipDuplicateMapInputs: true,",
						"     skipDuplicateMapOutputs: true,",
						"     errorHandlingOption: 'stopOnFirstError',",
						"     mapColumn(",
						"          TitleCode,",
						"          TitleDescription",
						"     )) ~> sink1"
					]
				}
			},
			"dependsOn": [
				"[concat(variables('factoryId'), '/datasets/ds_TitleMaster')]",
				"[concat(variables('factoryId'), '/datasets/ds_synapse_TITLE_MD')]"
			]
		},
		{
			"name": "[concat(parameters('factoryName'), '/df_Aggregate_Data')]",
			"type": "Microsoft.DataFactory/factories/dataflows",
			"apiVersion": "2018-06-01",
			"properties": {
				"type": "MappingDataFlow",
				"typeProperties": {
					"sources": [
						{
							"dataset": {
								"referenceName": "ds_sql_nyc_payroll",
								"type": "DatasetReference"
							},
							"name": "sourceSQLDB"
						},
						{
							"dataset": {
								"referenceName": "ds_Historical_Payroll",
								"type": "DatasetReference"
							},
							"name": "sourceHistory"
						}
					],
					"sinks": [
						{
							"dataset": {
								"referenceName": "ds_SYN_Payroll_Summary",
								"type": "DatasetReference"
							},
							"name": "sinkPayrollSummary"
						}
					],
					"transformations": [
						{
							"name": "unionNYCPayroll"
						},
						{
							"name": "filterFiscalYear"
						},
						{
							"name": "TotalPaidderivedColumn"
						},
						{
							"name": "aggregate"
						}
					],
					"scriptLines": [
						"parameters{",
						"     dataflow_param_fiscalyear as integer (2020)",
						"}",
						"source(output(",
						"          FiscalYear as integer,",
						"          PayrollNumber as integer,",
						"          AgencyID as integer,",
						"          AgencyName as string,",
						"          EmployeeID as integer,",
						"          LastName as string,",
						"          FirstName as string,",
						"          AgencyStartDate as date,",
						"          WorkLocationBorough as string,",
						"          TitleCode as integer,",
						"          TitleDescription as string,",
						"          LeaveStatusasofJune30 as string,",
						"          BaseSalary as double,",
						"          PayBasis as string,",
						"          RegularHours as double,",
						"          RegularGrossPaid as double,",
						"          OTHours as double,",
						"          TotalOTPaid as double,",
						"          TotalOtherPay as double",
						"     ),",
						"     allowSchemaDrift: true,",
						"     validateSchema: false,",
						"     isolationLevel: 'READ_UNCOMMITTED',",
						"     format: 'table') ~> sourceSQLDB",
						"source(output(",
						"          FiscalYear as integer,",
						"          PayrollNumber as integer,",
						"          AgencyID as integer,",
						"          AgencyName as string,",
						"          EmployeeID as integer,",
						"          LastName as string,",
						"          FirstName as string,",
						"          AgencyStartDate as date,",
						"          WorkLocationBorough as string,",
						"          TitleCode as integer,",
						"          TitleDescription as string,",
						"          LeaveStatusasofJune30 as string,",
						"          BaseSalary as double,",
						"          PayBasis as string,",
						"          RegularHours as double,",
						"          RegularGrossPaid as double,",
						"          OTHours as double,",
						"          TotalOTPaid as double,",
						"          TotalOtherPay as double",
						"     ),",
						"     allowSchemaDrift: true,",
						"     validateSchema: false,",
						"     ignoreNoFilesFound: false) ~> sourceHistory",
						"sourceSQLDB, sourceHistory union(byName: true)~> unionNYCPayroll",
						"unionNYCPayroll filter(FiscalYear >=$dataflow_param_fiscalyear) ~> filterFiscalYear",
						"filterFiscalYear derive(TotalPaid = RegularGrossPaid + TotalOTPaid + TotalOtherPay) ~> TotalPaidderivedColumn",
						"TotalPaidderivedColumn aggregate(groupBy(AgencyName,",
						"          FiscalYear),",
						"     TotalPaid = sum(TotalPaid)) ~> aggregate",
						"aggregate sink(allowSchemaDrift: true,",
						"     validateSchema: false,",
						"     input(",
						"          FiscalYear as integer,",
						"          AgencyName as string,",
						"          TotalPaid as double",
						"     ),",
						"     deletable:false,",
						"     insertable:true,",
						"     updateable:false,",
						"     upsertable:false,",
						"     truncate:true,",
						"     format: 'table',",
						"     staged: true,",
						"     allowCopyCommand: true,",
						"     skipDuplicateMapInputs: true,",
						"     skipDuplicateMapOutputs: true,",
						"     errorHandlingOption: 'stopOnFirstError',",
						"     mapColumn(",
						"          FiscalYear,",
						"          AgencyName,",
						"          TotalPaid",
						"     )) ~> sinkPayrollSummary"
					]
				}
			},
			"dependsOn": [
				"[concat(variables('factoryId'), '/datasets/ds_sql_nyc_payroll')]",
				"[concat(variables('factoryId'), '/datasets/ds_Historical_Payroll')]",
				"[concat(variables('factoryId'), '/datasets/ds_SYN_Payroll_Summary')]"
			]
		}
	]
}